{
  "importBase": "import",
  "nativeBase": "native",
  "name": "lobby",
  "deps": ["base", "main", "mini"],
  "uuids": [
    "0cpvKqE+1JpIrkuhfQnx/L",
    "8dK4ffKV1AcpzD3M0CZ+P4",
    "94wl9D3mlOEYbppegyjToQ",
    "aeUkkS6YZNJamMbCHYZfhi",
    "0cpvKqE+1JpIrkuhfQnx/L@6c48a",
    "0cpvKqE+1JpIrkuhfQnx/L@f9941",
    "18xh9b3qpPybbAuJ5+tUdS",
    "1e7b59765",
    "28tK6nr2dLX5obcV+8b/tv@f9941",
    "2bcZXT9tJCnY3ST1SCQHqr",
    "36SZtODcBIcriZIJProtP8@f9941",
    "41Nwfse2hO/aMNC9SN+utE",
    "546LvGSM1K0by9Qhf0PZ2W",
    "60goe4IEJMAIOAqyWB/+bS",
    "60goe4IEJMAIOAqyWB/+bS@0d9ce",
    "60goe4IEJMAIOAqyWB/+bS@11823",
    "60goe4IEJMAIOAqyWB/+bS@19002",
    "60goe4IEJMAIOAqyWB/+bS@19dc8",
    "60goe4IEJMAIOAqyWB/+bS@1ae95",
    "60goe4IEJMAIOAqyWB/+bS@1d21a",
    "60goe4IEJMAIOAqyWB/+bS@1e39f",
    "60goe4IEJMAIOAqyWB/+bS@1e79c",
    "60goe4IEJMAIOAqyWB/+bS@2d04b",
    "60goe4IEJMAIOAqyWB/+bS@32df0",
    "60goe4IEJMAIOAqyWB/+bS@345a5",
    "60goe4IEJMAIOAqyWB/+bS@3e465",
    "60goe4IEJMAIOAqyWB/+bS@3f373",
    "60goe4IEJMAIOAqyWB/+bS@48545",
    "60goe4IEJMAIOAqyWB/+bS@4ec15",
    "60goe4IEJMAIOAqyWB/+bS@5566c",
    "60goe4IEJMAIOAqyWB/+bS@55b3a",
    "60goe4IEJMAIOAqyWB/+bS@59373",
    "60goe4IEJMAIOAqyWB/+bS@5beca",
    "60goe4IEJMAIOAqyWB/+bS@62588",
    "60goe4IEJMAIOAqyWB/+bS@6330c",
    "60goe4IEJMAIOAqyWB/+bS@6862a",
    "60goe4IEJMAIOAqyWB/+bS@6fd0e",
    "60goe4IEJMAIOAqyWB/+bS@75302",
    "60goe4IEJMAIOAqyWB/+bS@7aaf6",
    "60goe4IEJMAIOAqyWB/+bS@7fb09",
    "60goe4IEJMAIOAqyWB/+bS@84920",
    "60goe4IEJMAIOAqyWB/+bS@8ab1e",
    "60goe4IEJMAIOAqyWB/+bS@8e5d7",
    "60goe4IEJMAIOAqyWB/+bS@9058f",
    "60goe4IEJMAIOAqyWB/+bS@917e7",
    "60goe4IEJMAIOAqyWB/+bS@94936",
    "60goe4IEJMAIOAqyWB/+bS@94eee",
    "60goe4IEJMAIOAqyWB/+bS@a2870",
    "60goe4IEJMAIOAqyWB/+bS@a44ef",
    "60goe4IEJMAIOAqyWB/+bS@ad702",
    "60goe4IEJMAIOAqyWB/+bS@ba9e1",
    "60goe4IEJMAIOAqyWB/+bS@cd79b",
    "60goe4IEJMAIOAqyWB/+bS@d8667",
    "60goe4IEJMAIOAqyWB/+bS@e08b2",
    "60goe4IEJMAIOAqyWB/+bS@e7fa9",
    "60goe4IEJMAIOAqyWB/+bS@f8379",
    "68jVBZxzRAzr5gkfSmxPK8@f9941",
    "6b4R19175NLIl0NhAINpkj",
    "74deKo2DhFMIC7abw+LMlO",
    "7enT0s1+FPh7THrvIfVdG4",
    "89r4cdTrVKxLaPeVdZOJU9@f9941",
    "8dK4ffKV1AcpzD3M0CZ+P4@6c48a",
    "91Z2H3e5FFu4oXLNlV0Nfd@f9941",
    "94wl9D3mlOEYbppegyjToQ@6c48a",
    "96lPBUahtF17wxJLfv4upu@f9941",
    "a6XG6oaj9Or6CcgIqlx6tP",
    "aeUkkS6YZNJamMbCHYZfhi@6c48a",
    "aeUkkS6YZNJamMbCHYZfhi@f9941",
    "b1uAJU4hFPLZ972QJejFn2",
    "b3pYhpxQ5H3pgC5EC/sWQn@f9941",
    "dfiiqVOo1DgpHJb7x5iXOu@f9941",
    "e0Ih1nz9VMr6RvtTfcuPWL",
    "e6lbn2rmpGlIUnnH8yNtbd@f9941",
    "e9w01J4cVI45AG8M1ZetLr@f9941",
    "eceH/r229L371k/j+47CqH",
    "eceH/r229L371k/j+47CqH@0206a",
    "eceH/r229L371k/j+47CqH@07ea7",
    "eceH/r229L371k/j+47CqH@0a832",
    "eceH/r229L371k/j+47CqH@0f09e",
    "eceH/r229L371k/j+47CqH@1a848",
    "eceH/r229L371k/j+47CqH@203e3",
    "eceH/r229L371k/j+47CqH@2205e",
    "eceH/r229L371k/j+47CqH@2cc97",
    "eceH/r229L371k/j+47CqH@33970",
    "eceH/r229L371k/j+47CqH@343b1",
    "eceH/r229L371k/j+47CqH@396e7",
    "eceH/r229L371k/j+47CqH@39fbb",
    "eceH/r229L371k/j+47CqH@3f837",
    "eceH/r229L371k/j+47CqH@416df",
    "eceH/r229L371k/j+47CqH@47756",
    "eceH/r229L371k/j+47CqH@54d24",
    "eceH/r229L371k/j+47CqH@58314",
    "eceH/r229L371k/j+47CqH@5ff02",
    "eceH/r229L371k/j+47CqH@68db4",
    "eceH/r229L371k/j+47CqH@6bb0e",
    "eceH/r229L371k/j+47CqH@6ec63",
    "eceH/r229L371k/j+47CqH@719bc",
    "eceH/r229L371k/j+47CqH@7cdec",
    "eceH/r229L371k/j+47CqH@7d2e2",
    "eceH/r229L371k/j+47CqH@7dd55",
    "eceH/r229L371k/j+47CqH@81e6f",
    "eceH/r229L371k/j+47CqH@8a4d3",
    "eceH/r229L371k/j+47CqH@8b750",
    "eceH/r229L371k/j+47CqH@8e63f",
    "eceH/r229L371k/j+47CqH@919cc",
    "eceH/r229L371k/j+47CqH@9bc51",
    "eceH/r229L371k/j+47CqH@9ea5e",
    "eceH/r229L371k/j+47CqH@ad0be",
    "eceH/r229L371k/j+47CqH@ae2c7",
    "eceH/r229L371k/j+47CqH@ae3eb",
    "eceH/r229L371k/j+47CqH@b6ef9",
    "eceH/r229L371k/j+47CqH@ba352",
    "eceH/r229L371k/j+47CqH@ba45f",
    "eceH/r229L371k/j+47CqH@d4dfb",
    "eceH/r229L371k/j+47CqH@d68b7",
    "eceH/r229L371k/j+47CqH@d79b6",
    "eceH/r229L371k/j+47CqH@e4432",
    "eceH/r229L371k/j+47CqH@e4e51",
    "eceH/r229L371k/j+47CqH@ef6ed",
    "eceH/r229L371k/j+47CqH@f6134",
    "eceH/r229L371k/j+47CqH@fe5e2",
    "f5LdHNTyNOlKMhEiBFiG9b@f9941",
    "fd/znc7r9Fwo9ksCR0Ptfm",
    "feSFVXx11EKrqTk5ju+SKa",
    "01c311b97",
    "1e7b59765@6c48a",
    "20g1ukYUVPvKWKBRznAKo+@f9941",
    "28bO9Y8sFOMaGKKDkuAOOd@f9941",
    "47abBfOP5I541eaTjr8TDS",
    "48+DL8MNpNyp6NHDd433yl@f9941",
    "51+6yFJUNMKKOXuOkfpgwX@f9941",
    "527XjsqHhPTqdQOfSbAhXK",
    "54TknWPwVPqJqeCR+Y/Czo@f9941",
    "58twCN/9VHfIQ0nwMM55Oe@f9941",
    "5cB79sOl1KDK2LFWyuNUpI@f9941",
    "6b/X5v4/JIT6bZEiwesAZP@f9941",
    "74ETy7EYVI27RATWnmUZn5@f9941",
    "7bESbOW+NNHKL43ILbSbWi",
    "7dj5uJT9FMn6OrOOx83tfK@f9941",
    "84b4zGD8ZKvoKT6K1fYNY/",
    "8esbilYiNIkZby76jDn6PS@f9941",
    "95EkngnxZFbYuFpsqVTaFr@f9941",
    "96fq/IA/NHFb9HIlMF2ASX",
    "9al8nUCLRD0onBrN1MEIdL@f9941",
    "9ek/IYeUVBB6RvHxav4L6L",
    "adi2rHnipCDpSzOpD//jAt@f9941",
    "c3VQfEAq9HNZ7k4yzIG7+X",
    "c5b7Df2ylC9Ybt5yRiyWSN",
    "dfZDOSL4xFGJEu571skHAc@f9941",
    "e8ay3we7tJz7mQfNGwKwJP",
    "e8p7JYiwtK3pve4otJ+nE1@f9941"
  ],
  "paths": {
    "0": ["sprites/common/bg", 3],
    "1": ["packed/lobby", 3],
    "2": ["packed/texture", 3],
    "3": ["sprites/notice/notice", 3],
    "4": ["sprites/common/bg/texture", 4, 1],
    "5": ["sprites/common/bg/spriteFrame", 2, 1],
    "6": ["prefabs/invitePopup", 0],
    "8": ["sprites/common/tab/spriteFrame", 2, 1],
    "9": ["prefabs/gameList", 0],
    "10": ["sprites/c5-xdl/spriteFrame", 2, 1],
    "11": ["prefabs/jackpot3LineSmall", 0],
    "13": ["packed/lobby", 1],
    "14": ["packed/lobby/ft_login", 2, 1],
    "15": ["packed/lobby/avatar_19", 2, 1],
    "16": ["packed/lobby/avatar_default", 2, 1],
    "17": ["packed/lobby/avatar_32", 2, 1],
    "18": ["packed/lobby/avatar_31", 2, 1],
    "19": ["packed/lobby/avatar_16", 2, 1],
    "20": ["packed/lobby/avatar_incognito", 2, 1],
    "21": ["packed/lobby/avatar_02", 2, 1],
    "22": ["packed/lobby/avatar_10", 2, 1],
    "23": ["packed/lobby/avatar_01", 2, 1],
    "24": ["packed/lobby/avatar_20", 2, 1],
    "25": ["packed/lobby/avatar_21", 2, 1],
    "26": ["packed/lobby/hd_login", 2, 1],
    "27": ["packed/lobby/jackpot", 2, 1],
    "28": ["packed/lobby/avatar_05", 2, 1],
    "29": ["packed/lobby/avatar_04", 2, 1],
    "30": ["packed/lobby/ft_logout", 2, 1],
    "31": ["packed/lobby/banner0", 2, 1],
    "32": ["packed/lobby/avatar_22", 2, 1],
    "33": ["packed/lobby/avatar_09", 2, 1],
    "34": ["packed/lobby/avatar_06", 2, 1],
    "35": ["packed/lobby/hd_logout_dl", 2, 1],
    "36": ["packed/lobby/avatar_30", 2, 1],
    "37": ["packed/lobby/avatar_17", 2, 1],
    "38": ["packed/lobby/avatar_28", 2, 1],
    "39": ["packed/lobby/avatar_18", 2, 1],
    "40": ["packed/lobby/avatar_29", 2, 1],
    "41": ["packed/lobby/avatar_empty", 2, 1],
    "42": ["packed/lobby/avatar_07", 2, 1],
    "43": ["packed/lobby/avatar_14", 2, 1],
    "44": ["packed/lobby/avatar_27", 2, 1],
    "45": ["packed/lobby/avatar_25", 2, 1],
    "46": ["packed/lobby/avatar_15", 2, 1],
    "47": ["packed/lobby/avatar_03", 2, 1],
    "48": ["packed/lobby/avatar_12", 2, 1],
    "49": ["packed/lobby/avatar_23", 2, 1],
    "50": ["packed/lobby/avatar_24", 2, 1],
    "51": ["packed/lobby/hd_logout", 2, 1],
    "52": ["packed/lobby/avatar_13", 2, 1],
    "53": ["packed/lobby/avatar_11", 2, 1],
    "54": ["packed/lobby/avatar_26", 2, 1],
    "55": ["packed/lobby/avatar_08", 2, 1],
    "56": ["sprites/common/lb_bg_new_mail2/spriteFrame", 2, 1],
    "57": ["prefabs/jackpot3Line", 0],
    "58": ["game", 0],
    "59": ["prefabs/createDisplayNamePopup", 0],
    "60": ["sprites/common/tab_active/spriteFrame", 2, 1],
    "61": ["packed/lobby/texture", 4, 1],
    "62": ["sprites/common/lb_icon_shield_2/spriteFrame", 2, 1],
    "63": ["packed/texture/texture", 4, 1],
    "64": ["sprites/common/banner_frame/spriteFrame", 2, 1],
    "65": ["prefabs/filter", 0],
    "66": ["sprites/notice/notice/texture", 4, 1],
    "67": ["sprites/notice/notice/spriteFrame", 2, 1],
    "68": ["prefabs/noticePopup", 0],
    "69": ["sprites/common/lb_icon_shield_1/spriteFrame", 2, 1],
    "70": ["sprites/common/frame/spriteFrame", 2, 1],
    "71": ["prefabs/jackpot1Line", 0],
    "72": ["sprites/common/lb_bg_new_mail/spriteFrame", 2, 1],
    "73": ["sprites/common/pt/spriteFrame", 2, 1],
    "74": ["packed/texture", 1],
    "75": ["packed/texture/ic_rongho", 2, 1],
    "76": ["packed/texture/xx_ic_sicbolive_c5", 2, 1],
    "77": ["packed/texture/ic_xocdia", 2, 1],
    "78": ["packed/texture/logo_a_sport", 2, 1],
    "79": ["packed/texture/ic_pokemon", 2, 1],
    "80": ["packed/texture/xx_ic_evolution", 2, 1],
    "81": ["packed/texture/logo_1", 2, 1],
    "82": ["packed/texture/logo_3", 2, 1],
    "83": ["packed/texture/logo_7", 2, 1],
    "84": ["packed/texture/ic_baucua", 2, 1],
    "85": ["packed/texture/ic_taixiu", 2, 1],
    "86": ["packed/texture/icon_lode", 2, 1],
    "87": ["packed/texture/xx_ic_via", 2, 1],
    "88": ["packed/texture/ic_mario", 2, 1],
    "89": ["packed/texture/xx_anim_ic_bac_c5", 2, 1],
    "90": ["packed/texture/ic_banca", 2, 1],
    "91": ["packed/texture/xx_ic_ngoai_sexygaming", 2, 1],
    "92": ["packed/texture/ic_axie", 2, 1],
    "93": ["packed/texture/ic_angrybirds", 2, 1],
    "94": ["packed/texture/ic_naruto", 2, 1],
    "95": ["packed/texture/ic_trutien", 2, 1],
    "96": ["packed/texture/ic_xdcm", 2, 1],
    "97": ["packed/texture/xx_ic_baucua_c5_x", 2, 1],
    "98": ["packed/texture/ic_lodenhanh", 2, 1],
    "99": ["packed/texture/ic_caothap", 2, 1],
    "100": ["packed/texture/ic_JL", 2, 1],
    "101": ["packed/texture/logo_5", 2, 1],
    "102": ["packed/texture/ic_sicbo", 2, 1],
    "103": ["packed/texture/ic_alladdin", 2, 1],
    "104": ["packed/texture/ic_duangua", 2, 1],
    "105": ["packed/texture/icon_spot", 2, 1],
    "106": ["packed/texture/ic_baucua5", 2, 1],
    "107": ["packed/texture/xx_ic_vivo", 2, 1],
    "108": ["packed/texture/ic_xdl", 2, 1],
    "109": ["packed/texture/ic_lanhailoc", 2, 1],
    "110": ["packed/texture/ic_pvz", 2, 1],
    "111": ["packed/texture/ic_xdsm", 2, 1],
    "112": ["packed/texture/logo_s_sport", 2, 1],
    "113": ["packed/texture/logo_8", 2, 1],
    "114": ["packed/texture/ic_minipoker", 2, 1],
    "115": ["packed/texture/logo_2", 2, 1],
    "116": ["packed/texture/logo_6", 2, 1],
    "117": ["packed/texture/ic_volta", 2, 1],
    "118": ["packed/texture/ic_thanbaimientay", 2, 1],
    "119": ["packed/texture/xx_ic_ronghp_c5_x", 2, 1],
    "120": ["packed/texture/ic_txl", 2, 1],
    "121": ["sprites/common/notifi/spriteFrame", 2, 1],
    "122": ["init", 0],
    "123": ["prefabs/slotTopJackpotView", 0]
  },
  "scenes": { "db://assets/bundles/lobby/game.scene": 12 },
  "packs": {
    "01c311b97": [
      "0",
      "4",
      "5",
      "6",
      "7",
      "125",
      "8",
      "9",
      "10",
      "11",
      "12",
      "13",
      "14",
      "15",
      "16",
      "17",
      "18",
      "19",
      "20",
      "21",
      "22",
      "23",
      "24",
      "25",
      "26",
      "27",
      "28",
      "29",
      "30",
      "31",
      "32",
      "33",
      "34",
      "35",
      "36",
      "37",
      "38",
      "39",
      "40",
      "41",
      "42",
      "43",
      "44",
      "45",
      "46",
      "47",
      "48",
      "49",
      "50",
      "51",
      "52",
      "53",
      "54",
      "55",
      "56",
      "57",
      "58",
      "59",
      "60",
      "1",
      "61",
      "62",
      "2",
      "63",
      "64",
      "65",
      "3",
      "66",
      "67",
      "68",
      "69",
      "70",
      "71",
      "72",
      "73",
      "74",
      "75",
      "76",
      "77",
      "78",
      "79",
      "80",
      "81",
      "82",
      "83",
      "84",
      "85",
      "86",
      "87",
      "88",
      "89",
      "90",
      "91",
      "92",
      "93",
      "94",
      "95",
      "96",
      "97",
      "98",
      "99",
      "100",
      "101",
      "102",
      "103",
      "104",
      "105",
      "106",
      "107",
      "108",
      "109",
      "110",
      "111",
      "112",
      "113",
      "114",
      "115",
      "116",
      "117",
      "118",
      "119",
      "120",
      "121",
      "122",
      "123"
    ]
  },
  "versions": {
    "import": [124, "f701d"],
    "native": [0, "c4ddf", 7, "2a841", 1, "091be", 2, "03be6", 3, "53a22"]
  },
  "redirect": [
    126,
    "1",
    127,
    "0",
    128,
    "0",
    129,
    "0",
    130,
    "0",
    131,
    "0",
    132,
    "1",
    133,
    "0",
    134,
    "0",
    135,
    "0",
    136,
    "0",
    137,
    "2",
    138,
    "1",
    139,
    "0",
    140,
    "0",
    141,
    "1",
    142,
    "0",
    143,
    "0",
    144,
    "1",
    145,
    "0",
    146,
    "0",
    147,
    "0",
    148,
    "0",
    149,
    "0",
    150,
    "0"
  ],
  "debug": false,
  "extensionMap": {},
  "types": [
    "cc.Prefab",
    "cc.SpriteAtlas",
    "cc.SpriteFrame",
    "cc.ImageAsset",
    "cc.Texture2D"
  ]
}
